telegram_simulation_bot/MITgcm.py
telegram_simulation_bot/__init__.py
telegram_simulation_bot/config.py
telegram_simulation_bot/handler.py
telegram_simulation_bot-0.1.3.data/scripts/telegram_simulation_bot
telegram_simulation_bot-0.1.3.dist-info/LICENSE
telegram_simulation_bot-0.1.3.dist-info/METADATA
telegram_simulation_bot-0.1.3.dist-info/WHEEL
telegram_simulation_bot-0.1.3.dist-info/top_level.txt
telegram_simulation_bot-0.1.3.dist-info/RECORD
