Metadata-Version: 2.1
Name: telegram-simulation-bot
Version: 0.1.3
Summary: Interact with your computing cluster via telegram to get realtime information on your running jobs.
Home-page: https://github.com/AaronDavidSchneider/telegram_simulation_bot
Author: Aaron David Schneider
Author-email: aarondavid.schneider@nbi.ku.dk
License: MIT
License-File: LICENSE
Requires-Dist: f90nml (>=1.3.1)
Requires-Dist: telethon
Requires-Dist: appdirs
Requires-Dist: pyyaml
